[
  {
    "id": "mock_飞鹤奶粉_0",
    "keyword": "飞鹤奶粉",
    "title": "飞鹤奶粉使用心得分享",
    "content": "最近给宝宝换了飞鹤奶粉，感觉还不错。宝宝喝了一个月，消化情况良好，没有出现便秘或者腹泻的情况。溶解度也可以，没有结块。价格方面稍微有点贵，但是为了宝宝的健康还是值得的。",
    "author": "用户15363",
    "likes": 339,
    "comments": 81,
    "publish_time": "2026-03-03",
    "url": "https://www.xiaohongshu.com/explore/844229486",
    "is_mock": true,
    "sentiment": 1,
    "base_sentiment": 0.997,
    "label": "正面",
    "keywords": [
      "宝宝",
      "飞鹤",
      "结块",
      "溶解度",
      "奶粉"
    ],
    "summary": [
      "但是为了宝宝的健康还是值得的",
      "没有出现便秘或者腹泻的情况",
      "消化情况良好"
    ],
    "positive_words_found": 4,
    "negative_words_found": 3
  },
  {
    "id": "mock_飞鹤奶粉_1",
    "keyword": "飞鹤奶粉",
    "title": "飞鹤奶粉真实测评",
    "content": "买了飞鹤奶粉之后有点失望。宝宝喝了之后有点上火，可能是配方不太适合。而且粉质不够细腻，冲泡的时候容易结块。",
    "author": "用户44039",
    "likes": 76,
    "comments": 19,
    "publish_time": "2026-03-03",
    "url": "https://www.xiaohongshu.com/explore/238514023",
    "is_mock": true,
    "sentiment": 0,
    "base_sentiment": 0.0423,
    "label": "负面",
    "keywords": [
      "飞鹤",
      "粉质",
      "结块",
      "有点",
      "冲泡"
    ],
    "summary": [
      "买了飞鹤奶粉之后有点失望",
      "宝宝喝了之后有点上火",
      "可能是配方不太适合"
    ],
    "positive_words_found": 0,
    "negative_words_found": 3
  },
  {
    "id": "mock_飞鹤奶粉_2",
    "keyword": "飞鹤奶粉",
    "title": "飞鹤奶粉使用心得分享",
    "content": "最近给宝宝换了飞鹤奶粉，感觉还不错。宝宝喝了一个月，消化情况良好，没有出现便秘或者腹泻的情况。溶解度也可以，没有结块。价格方面稍微有点贵，但是为了宝宝的健康还是值得的。",
    "author": "用户15451",
    "likes": 319,
    "comments": 75,
    "publish_time": "2026-03-03",
    "url": "https://www.xiaohongshu.com/explore/490182428",
    "is_mock": true,
    "sentiment": 1,
    "base_sentiment": 0.997,
    "label": "正面",
    "keywords": [
      "宝宝",
      "飞鹤",
      "结块",
      "溶解度",
      "奶粉"
    ],
    "summary": [
      "但是为了宝宝的健康还是值得的",
      "没有出现便秘或者腹泻的情况",
      "消化情况良好"
    ],
    "positive_words_found": 4,
    "negative_words_found": 3
  },
  {
    "id": "mock_飞鹤奶粉_3",
    "keyword": "飞鹤奶粉",
    "title": "飞鹤奶粉真实测评",
    "content": "买了飞鹤奶粉之后有点失望。宝宝喝了之后有点上火，可能是配方不太适合。而且粉质不够细腻，冲泡的时候容易结块。",
    "author": "用户26201",
    "likes": 83,
    "comments": 27,
    "publish_time": "2026-03-03",
    "url": "https://www.xiaohongshu.com/explore/205001056",
    "is_mock": true,
    "sentiment": 0,
    "base_sentiment": 0.0423,
    "label": "负面",
    "keywords": [
      "飞鹤",
      "粉质",
      "结块",
      "有点",
      "冲泡"
    ],
    "summary": [
      "买了飞鹤奶粉之后有点失望",
      "宝宝喝了之后有点上火",
      "可能是配方不太适合"
    ],
    "positive_words_found": 0,
    "negative_words_found": 3
  },
  {
    "id": "mock_飞鹤奶粉_4",
    "keyword": "飞鹤奶粉",
    "title": "飞鹤奶粉使用心得分享",
    "content": "最近给宝宝换了飞鹤奶粉，感觉还不错。宝宝喝了一个月，消化情况良好，没有出现便秘或者腹泻的情况。溶解度也可以，没有结块。价格方面稍微有点贵，但是为了宝宝的健康还是值得的。",
    "author": "用户78435",
    "likes": 336,
    "comments": 78,
    "publish_time": "2026-03-03",
    "url": "https://www.xiaohongshu.com/explore/844532128",
    "is_mock": true,
    "sentiment": 1,
    "base_sentiment": 0.997,
    "label": "正面",
    "keywords": [
      "宝宝",
      "飞鹤",
      "结块",
      "溶解度",
      "奶粉"
    ],
    "summary": [
      "但是为了宝宝的健康还是值得的",
      "没有出现便秘或者腹泻的情况",
      "消化情况良好"
    ],
    "positive_words_found": 4,
    "negative_words_found": 3
  },
  {
    "id": "mock_飞鹤奶粉_5",
    "keyword": "飞鹤奶粉",
    "title": "飞鹤奶粉真实测评",
    "content": "买了飞鹤奶粉之后有点失望。宝宝喝了之后有点上火，可能是配方不太适合。而且粉质不够细腻，冲泡的时候容易结块。",
    "author": "用户74207",
    "likes": 89,
    "comments": 28,
    "publish_time": "2026-03-03",
    "url": "https://www.xiaohongshu.com/explore/272597590",
    "is_mock": true,
    "sentiment": 0,
    "base_sentiment": 0.0423,
    "label": "负面",
    "keywords": [
      "飞鹤",
      "粉质",
      "结块",
      "有点",
      "冲泡"
    ],
    "summary": [
      "买了飞鹤奶粉之后有点失望",
      "宝宝喝了之后有点上火",
      "可能是配方不太适合"
    ],
    "positive_words_found": 0,
    "negative_words_found": 3
  },
  {
    "id": "mock_飞鹤奶粉_6",
    "keyword": "飞鹤奶粉",
    "title": "飞鹤奶粉使用心得分享",
    "content": "最近给宝宝换了飞鹤奶粉，感觉还不错。宝宝喝了一个月，消化情况良好，没有出现便秘或者腹泻的情况。溶解度也可以，没有结块。价格方面稍微有点贵，但是为了宝宝的健康还是值得的。",
    "author": "用户65275",
    "likes": 327,
    "comments": 72,
    "publish_time": "2026-03-03",
    "url": "https://www.xiaohongshu.com/explore/964672349",
    "is_mock": true,
    "sentiment": 1,
    "base_sentiment": 0.997,
    "label": "正面",
    "keywords": [
      "宝宝",
      "飞鹤",
      "结块",
      "溶解度",
      "奶粉"
    ],
    "summary": [
      "但是为了宝宝的健康还是值得的",
      "没有出现便秘或者腹泻的情况",
      "消化情况良好"
    ],
    "positive_words_found": 4,
    "negative_words_found": 3
  },
  {
    "id": "mock_飞鹤奶粉_7",
    "keyword": "飞鹤奶粉",
    "title": "飞鹤奶粉真实测评",
    "content": "买了飞鹤奶粉之后有点失望。宝宝喝了之后有点上火，可能是配方不太适合。而且粉质不够细腻，冲泡的时候容易结块。",
    "author": "用户49070",
    "likes": 87,
    "comments": 28,
    "publish_time": "2026-03-03",
    "url": "https://www.xiaohongshu.com/explore/942095428",
    "is_mock": true,
    "sentiment": 0,
    "base_sentiment": 0.0423,
    "label": "负面",
    "keywords": [
      "飞鹤",
      "粉质",
      "结块",
      "有点",
      "冲泡"
    ],
    "summary": [
      "买了飞鹤奶粉之后有点失望",
      "宝宝喝了之后有点上火",
      "可能是配方不太适合"
    ],
    "positive_words_found": 0,
    "negative_words_found": 3
  },
  {
    "id": "mock_飞鹤奶粉_8",
    "keyword": "飞鹤奶粉",
    "title": "飞鹤奶粉使用心得分享",
    "content": "最近给宝宝换了飞鹤奶粉，感觉还不错。宝宝喝了一个月，消化情况良好，没有出现便秘或者腹泻的情况。溶解度也可以，没有结块。价格方面稍微有点贵，但是为了宝宝的健康还是值得的。",
    "author": "用户34614",
    "likes": 335,
    "comments": 81,
    "publish_time": "2026-03-03",
    "url": "https://www.xiaohongshu.com/explore/161500320",
    "is_mock": true,
    "sentiment": 1,
    "base_sentiment": 0.997,
    "label": "正面",
    "keywords": [
      "宝宝",
      "飞鹤",
      "结块",
      "溶解度",
      "奶粉"
    ],
    "summary": [
      "但是为了宝宝的健康还是值得的",
      "没有出现便秘或者腹泻的情况",
      "消化情况良好"
    ],
    "positive_words_found": 4,
    "negative_words_found": 3
  },
  {
    "id": "mock_飞鹤奶粉_9",
    "keyword": "飞鹤奶粉",
    "title": "飞鹤奶粉真实测评",
    "content": "买了飞鹤奶粉之后有点失望。宝宝喝了之后有点上火，可能是配方不太适合。而且粉质不够细腻，冲泡的时候容易结块。",
    "author": "用户17807",
    "likes": 68,
    "comments": 28,
    "publish_time": "2026-03-03",
    "url": "https://www.xiaohongshu.com/explore/996373241",
    "is_mock": true,
    "sentiment": 0,
    "base_sentiment": 0.0423,
    "label": "负面",
    "keywords": [
      "飞鹤",
      "粉质",
      "结块",
      "有点",
      "冲泡"
    ],
    "summary": [
      "买了飞鹤奶粉之后有点失望",
      "宝宝喝了之后有点上火",
      "可能是配方不太适合"
    ],
    "positive_words_found": 0,
    "negative_words_found": 3
  },
  {
    "id": "mock_爱他美_0",
    "keyword": "爱他美",
    "title": "爱他美使用心得分享",
    "content": "最近给宝宝换了爱他美，感觉还不错。宝宝喝了一个月，消化情况良好，没有出现便秘或者腹泻的情况。溶解度也可以，没有结块。价格方面稍微有点贵，但是为了宝宝的健康还是值得的。",
    "author": "用户86397",
    "likes": 93,
    "comments": 99,
    "publish_time": "2026-03-03",
    "url": "https://www.xiaohongshu.com/explore/817483603",
    "is_mock": true,
    "sentiment": 1,
    "base_sentiment": 0.9968,
    "label": "正面",
    "keywords": [
      "宝宝",
      "结块",
      "溶解度",
      "腹泻",
      "便秘"
    ],
    "summary": [
      "但是为了宝宝的健康还是值得的",
      "消化情况良好",
      "没有出现便秘或者腹泻的情况"
    ],
    "positive_words_found": 4,
    "negative_words_found": 3
  },
  {
    "id": "mock_爱他美_1",
    "keyword": "爱他美",
    "title": "爱他美真实测评",
    "content": "买了爱他美之后有点失望。宝宝喝了之后有点上火，可能是配方不太适合。而且粉质不够细腻，冲泡的时候容易结块。",
    "author": "用户80197",
    "likes": 99,
    "comments": 17,
    "publish_time": "2026-03-03",
    "url": "https://www.xiaohongshu.com/explore/165621898",
    "is_mock": true,
    "sentiment": 0,
    "base_sentiment": 0.04,
    "label": "负面",
    "keywords": [
      "粉质",
      "结块",
      "有点",
      "冲泡",
      "上火"
    ],
    "summary": [
      "买了爱他美之后有点失望",
      "宝宝喝了之后有点上火",
      "可能是配方不太适合"
    ],
    "positive_words_found": 0,
    "negative_words_found": 3
  },
  {
    "id": "mock_爱他美_2",
    "keyword": "爱他美",
    "title": "爱他美使用心得分享",
    "content": "最近给宝宝换了爱他美，感觉还不错。宝宝喝了一个月，消化情况良好，没有出现便秘或者腹泻的情况。溶解度也可以，没有结块。价格方面稍微有点贵，但是为了宝宝的健康还是值得的。",
    "author": "用户13551",
    "likes": 94,
    "comments": 98,
    "publish_time": "2026-03-03",
    "url": "https://www.xiaohongshu.com/explore/889019498",
    "is_mock": true,
    "sentiment": 1,
    "base_sentiment": 0.9968,
    "label": "正面",
    "keywords": [
      "宝宝",
      "结块",
      "溶解度",
      "腹泻",
      "便秘"
    ],
    "summary": [
      "但是为了宝宝的健康还是值得的",
      "消化情况良好",
      "没有出现便秘或者腹泻的情况"
    ],
    "positive_words_found": 4,
    "negative_words_found": 3
  },
  {
    "id": "mock_爱他美_3",
    "keyword": "爱他美",
    "title": "爱他美真实测评",
    "content": "买了爱他美之后有点失望。宝宝喝了之后有点上火，可能是配方不太适合。而且粉质不够细腻，冲泡的时候容易结块。",
    "author": "用户97118",
    "likes": 116,
    "comments": 15,
    "publish_time": "2026-03-03",
    "url": "https://www.xiaohongshu.com/explore/576550148",
    "is_mock": true,
    "sentiment": 0,
    "base_sentiment": 0.04,
    "label": "负面",
    "keywords": [
      "粉质",
      "结块",
      "有点",
      "冲泡",
      "上火"
    ],
    "summary": [
      "买了爱他美之后有点失望",
      "宝宝喝了之后有点上火",
      "可能是配方不太适合"
    ],
    "positive_words_found": 0,
    "negative_words_found": 3
  },
  {
    "id": "mock_爱他美_4",
    "keyword": "爱他美",
    "title": "爱他美使用心得分享",
    "content": "最近给宝宝换了爱他美，感觉还不错。宝宝喝了一个月，消化情况良好，没有出现便秘或者腹泻的情况。溶解度也可以，没有结块。价格方面稍微有点贵，但是为了宝宝的健康还是值得的。",
    "author": "用户10939",
    "likes": 73,
    "comments": 103,
    "publish_time": "2026-03-03",
    "url": "https://www.xiaohongshu.com/explore/817168449",
    "is_mock": true,
    "sentiment": 1,
    "base_sentiment": 0.9968,
    "label": "正面",
    "keywords": [
      "宝宝",
      "结块",
      "溶解度",
      "腹泻",
      "便秘"
    ],
    "summary": [
      "但是为了宝宝的健康还是值得的",
      "消化情况良好",
      "没有出现便秘或者腹泻的情况"
    ],
    "positive_words_found": 4,
    "negative_words_found": 3
  },
  {
    "id": "mock_爱他美_5",
    "keyword": "爱他美",
    "title": "爱他美真实测评",
    "content": "买了爱他美之后有点失望。宝宝喝了之后有点上火，可能是配方不太适合。而且粉质不够细腻，冲泡的时候容易结块。",
    "author": "用户82988",
    "likes": 114,
    "comments": 14,
    "publish_time": "2026-03-03",
    "url": "https://www.xiaohongshu.com/explore/501328071",
    "is_mock": true,
    "sentiment": 0,
    "base_sentiment": 0.04,
    "label": "负面",
    "keywords": [
      "粉质",
      "结块",
      "有点",
      "冲泡",
      "上火"
    ],
    "summary": [
      "买了爱他美之后有点失望",
      "宝宝喝了之后有点上火",
      "可能是配方不太适合"
    ],
    "positive_words_found": 0,
    "negative_words_found": 3
  },
  {
    "id": "mock_爱他美_6",
    "keyword": "爱他美",
    "title": "爱他美使用心得分享",
    "content": "最近给宝宝换了爱他美，感觉还不错。宝宝喝了一个月，消化情况良好，没有出现便秘或者腹泻的情况。溶解度也可以，没有结块。价格方面稍微有点贵，但是为了宝宝的健康还是值得的。",
    "author": "用户61336",
    "likes": 79,
    "comments": 99,
    "publish_time": "2026-03-03",
    "url": "https://www.xiaohongshu.com/explore/393528173",
    "is_mock": true,
    "sentiment": 1,
    "base_sentiment": 0.9968,
    "label": "正面",
    "keywords": [
      "宝宝",
      "结块",
      "溶解度",
      "腹泻",
      "便秘"
    ],
    "summary": [
      "但是为了宝宝的健康还是值得的",
      "消化情况良好",
      "没有出现便秘或者腹泻的情况"
    ],
    "positive_words_found": 4,
    "negative_words_found": 3
  },
  {
    "id": "mock_爱他美_7",
    "keyword": "爱他美",
    "title": "爱他美真实测评",
    "content": "买了爱他美之后有点失望。宝宝喝了之后有点上火，可能是配方不太适合。而且粉质不够细腻，冲泡的时候容易结块。",
    "author": "用户67909",
    "likes": 123,
    "comments": 13,
    "publish_time": "2026-03-03",
    "url": "https://www.xiaohongshu.com/explore/598341068",
    "is_mock": true,
    "sentiment": 0,
    "base_sentiment": 0.04,
    "label": "负面",
    "keywords": [
      "粉质",
      "结块",
      "有点",
      "冲泡",
      "上火"
    ],
    "summary": [
      "买了爱他美之后有点失望",
      "宝宝喝了之后有点上火",
      "可能是配方不太适合"
    ],
    "positive_words_found": 0,
    "negative_words_found": 3
  },
  {
    "id": "mock_爱他美_8",
    "keyword": "爱他美",
    "title": "爱他美使用心得分享",
    "content": "最近给宝宝换了爱他美，感觉还不错。宝宝喝了一个月，消化情况良好，没有出现便秘或者腹泻的情况。溶解度也可以，没有结块。价格方面稍微有点贵，但是为了宝宝的健康还是值得的。",
    "author": "用户98037",
    "likes": 65,
    "comments": 98,
    "publish_time": "2026-03-03",
    "url": "https://www.xiaohongshu.com/explore/918763964",
    "is_mock": true,
    "sentiment": 1,
    "base_sentiment": 0.9968,
    "label": "正面",
    "keywords": [
      "宝宝",
      "结块",
      "溶解度",
      "腹泻",
      "便秘"
    ],
    "summary": [
      "但是为了宝宝的健康还是值得的",
      "消化情况良好",
      "没有出现便秘或者腹泻的情况"
    ],
    "positive_words_found": 4,
    "negative_words_found": 3
  },
  {
    "id": "mock_爱他美_9",
    "keyword": "爱他美",
    "title": "爱他美真实测评",
    "content": "买了爱他美之后有点失望。宝宝喝了之后有点上火，可能是配方不太适合。而且粉质不够细腻，冲泡的时候容易结块。",
    "author": "用户65938",
    "likes": 98,
    "comments": 16,
    "publish_time": "2026-03-03",
    "url": "https://www.xiaohongshu.com/explore/244976124",
    "is_mock": true,
    "sentiment": 0,
    "base_sentiment": 0.04,
    "label": "负面",
    "keywords": [
      "粉质",
      "结块",
      "有点",
      "冲泡",
      "上火"
    ],
    "summary": [
      "买了爱他美之后有点失望",
      "宝宝喝了之后有点上火",
      "可能是配方不太适合"
    ],
    "positive_words_found": 0,
    "negative_words_found": 3
  },
  {
    "id": "mock_美赞臣_0",
    "keyword": "美赞臣",
    "title": "美赞臣使用心得分享",
    "content": "最近给宝宝换了美赞臣，感觉还不错。宝宝喝了一个月，消化情况良好，没有出现便秘或者腹泻的情况。溶解度也可以，没有结块。价格方面稍微有点贵，但是为了宝宝的健康还是值得的。",
    "author": "用户56383",
    "likes": 163,
    "comments": 25,
    "publish_time": "2026-03-03",
    "url": "https://www.xiaohongshu.com/explore/958567680",
    "is_mock": true,
    "sentiment": 1,
    "base_sentiment": 0.9906,
    "label": "正面",
    "keywords": [
      "宝宝",
      "美赞臣",
      "结块",
      "溶解度",
      "腹泻"
    ],
    "summary": [
      "但是为了宝宝的健康还是值得的",
      "消化情况良好",
      "没有出现便秘或者腹泻的情况"
    ],
    "positive_words_found": 4,
    "negative_words_found": 3
  },
  {
    "id": "mock_美赞臣_1",
    "keyword": "美赞臣",
    "title": "美赞臣真实测评",
    "content": "买了美赞臣之后有点失望。宝宝喝了之后有点上火，可能是配方不太适合。而且粉质不够细腻，冲泡的时候容易结块。",
    "author": "用户51061",
    "likes": 151,
    "comments": 38,
    "publish_time": "2026-03-03",
    "url": "https://www.xiaohongshu.com/explore/272229290",
    "is_mock": true,
    "sentiment": 0,
    "base_sentiment": 0.0138,
    "label": "负面",
    "keywords": [
      "美赞臣",
      "粉质",
      "结块",
      "有点",
      "冲泡"
    ],
    "summary": [
      "买了美赞臣之后有点失望",
      "宝宝喝了之后有点上火",
      "可能是配方不太适合"
    ],
    "positive_words_found": 0,
    "negative_words_found": 3
  },
  {
    "id": "mock_美赞臣_2",
    "keyword": "美赞臣",
    "title": "美赞臣使用心得分享",
    "content": "最近给宝宝换了美赞臣，感觉还不错。宝宝喝了一个月，消化情况良好，没有出现便秘或者腹泻的情况。溶解度也可以，没有结块。价格方面稍微有点贵，但是为了宝宝的健康还是值得的。",
    "author": "用户91624",
    "likes": 160,
    "comments": 25,
    "publish_time": "2026-03-03",
    "url": "https://www.xiaohongshu.com/explore/591801319",
    "is_mock": true,
    "sentiment": 1,
    "base_sentiment": 0.9906,
    "label": "正面",
    "keywords": [
      "宝宝",
      "美赞臣",
      "结块",
      "溶解度",
      "腹泻"
    ],
    "summary": [
      "但是为了宝宝的健康还是值得的",
      "消化情况良好",
      "没有出现便秘或者腹泻的情况"
    ],
    "positive_words_found": 4,
    "negative_words_found": 3
  },
  {
    "id": "mock_美赞臣_3",
    "keyword": "美赞臣",
    "title": "美赞臣真实测评",
    "content": "买了美赞臣之后有点失望。宝宝喝了之后有点上火，可能是配方不太适合。而且粉质不够细腻，冲泡的时候容易结块。",
    "author": "用户58686",
    "likes": 160,
    "comments": 40,
    "publish_time": "2026-03-03",
    "url": "https://www.xiaohongshu.com/explore/518627490",
    "is_mock": true,
    "sentiment": 0,
    "base_sentiment": 0.0138,
    "label": "负面",
    "keywords": [
      "美赞臣",
      "粉质",
      "结块",
      "有点",
      "冲泡"
    ],
    "summary": [
      "买了美赞臣之后有点失望",
      "宝宝喝了之后有点上火",
      "可能是配方不太适合"
    ],
    "positive_words_found": 0,
    "negative_words_found": 3
  },
  {
    "id": "mock_美赞臣_4",
    "keyword": "美赞臣",
    "title": "美赞臣使用心得分享",
    "content": "最近给宝宝换了美赞臣，感觉还不错。宝宝喝了一个月，消化情况良好，没有出现便秘或者腹泻的情况。溶解度也可以，没有结块。价格方面稍微有点贵，但是为了宝宝的健康还是值得的。",
    "author": "用户13636",
    "likes": 162,
    "comments": 20,
    "publish_time": "2026-03-03",
    "url": "https://www.xiaohongshu.com/explore/748845652",
    "is_mock": true,
    "sentiment": 1,
    "base_sentiment": 0.9906,
    "label": "正面",
    "keywords": [
      "宝宝",
      "美赞臣",
      "结块",
      "溶解度",
      "腹泻"
    ],
    "summary": [
      "但是为了宝宝的健康还是值得的",
      "消化情况良好",
      "没有出现便秘或者腹泻的情况"
    ],
    "positive_words_found": 4,
    "negative_words_found": 3
  },
  {
    "id": "mock_美赞臣_5",
    "keyword": "美赞臣",
    "title": "美赞臣真实测评",
    "content": "买了美赞臣之后有点失望。宝宝喝了之后有点上火，可能是配方不太适合。而且粉质不够细腻，冲泡的时候容易结块。",
    "author": "用户17626",
    "likes": 176,
    "comments": 32,
    "publish_time": "2026-03-03",
    "url": "https://www.xiaohongshu.com/explore/485383415",
    "is_mock": true,
    "sentiment": 0,
    "base_sentiment": 0.0138,
    "label": "负面",
    "keywords": [
      "美赞臣",
      "粉质",
      "结块",
      "有点",
      "冲泡"
    ],
    "summary": [
      "买了美赞臣之后有点失望",
      "宝宝喝了之后有点上火",
      "可能是配方不太适合"
    ],
    "positive_words_found": 0,
    "negative_words_found": 3
  },
  {
    "id": "mock_美赞臣_6",
    "keyword": "美赞臣",
    "title": "美赞臣使用心得分享",
    "content": "最近给宝宝换了美赞臣，感觉还不错。宝宝喝了一个月，消化情况良好，没有出现便秘或者腹泻的情况。溶解度也可以，没有结块。价格方面稍微有点贵，但是为了宝宝的健康还是值得的。",
    "author": "用户21249",
    "likes": 164,
    "comments": 27,
    "publish_time": "2026-03-03",
    "url": "https://www.xiaohongshu.com/explore/476647106",
    "is_mock": true,
    "sentiment": 1,
    "base_sentiment": 0.9906,
    "label": "正面",
    "keywords": [
      "宝宝",
      "美赞臣",
      "结块",
      "溶解度",
      "腹泻"
    ],
    "summary": [
      "但是为了宝宝的健康还是值得的",
      "消化情况良好",
      "没有出现便秘或者腹泻的情况"
    ],
    "positive_words_found": 4,
    "negative_words_found": 3
  },
  {
    "id": "mock_美赞臣_7",
    "keyword": "美赞臣",
    "title": "美赞臣真实测评",
    "content": "买了美赞臣之后有点失望。宝宝喝了之后有点上火，可能是配方不太适合。而且粉质不够细腻，冲泡的时候容易结块。",
    "author": "用户19823",
    "likes": 184,
    "comments": 41,
    "publish_time": "2026-03-03",
    "url": "https://www.xiaohongshu.com/explore/179009196",
    "is_mock": true,
    "sentiment": 0,
    "base_sentiment": 0.0138,
    "label": "负面",
    "keywords": [
      "美赞臣",
      "粉质",
      "结块",
      "有点",
      "冲泡"
    ],
    "summary": [
      "买了美赞臣之后有点失望",
      "宝宝喝了之后有点上火",
      "可能是配方不太适合"
    ],
    "positive_words_found": 0,
    "negative_words_found": 3
  },
  {
    "id": "mock_美赞臣_8",
    "keyword": "美赞臣",
    "title": "美赞臣使用心得分享",
    "content": "最近给宝宝换了美赞臣，感觉还不错。宝宝喝了一个月，消化情况良好，没有出现便秘或者腹泻的情况。溶解度也可以，没有结块。价格方面稍微有点贵，但是为了宝宝的健康还是值得的。",
    "author": "用户51883",
    "likes": 175,
    "comments": 29,
    "publish_time": "2026-03-03",
    "url": "https://www.xiaohongshu.com/explore/596276009",
    "is_mock": true,
    "sentiment": 1,
    "base_sentiment": 0.9906,
    "label": "正面",
    "keywords": [
      "宝宝",
      "美赞臣",
      "结块",
      "溶解度",
      "腹泻"
    ],
    "summary": [
      "但是为了宝宝的健康还是值得的",
      "消化情况良好",
      "没有出现便秘或者腹泻的情况"
    ],
    "positive_words_found": 4,
    "negative_words_found": 3
  },
  {
    "id": "mock_美赞臣_9",
    "keyword": "美赞臣",
    "title": "美赞臣真实测评",
    "content": "买了美赞臣之后有点失望。宝宝喝了之后有点上火，可能是配方不太适合。而且粉质不够细腻，冲泡的时候容易结块。",
    "author": "用户58847",
    "likes": 181,
    "comments": 35,
    "publish_time": "2026-03-03",
    "url": "https://www.xiaohongshu.com/explore/409219416",
    "is_mock": true,
    "sentiment": 0,
    "base_sentiment": 0.0138,
    "label": "负面",
    "keywords": [
      "美赞臣",
      "粉质",
      "结块",
      "有点",
      "冲泡"
    ],
    "summary": [
      "买了美赞臣之后有点失望",
      "宝宝喝了之后有点上火",
      "可能是配方不太适合"
    ],
    "positive_words_found": 0,
    "negative_words_found": 3
  },
  {
    "id": "mock_惠氏_0",
    "keyword": "惠氏",
    "title": "惠氏使用心得分享",
    "content": "最近给宝宝换了惠氏，感觉还不错。宝宝喝了一个月，消化情况良好，没有出现便秘或者腹泻的情况。溶解度也可以，没有结块。价格方面稍微有点贵，但是为了宝宝的健康还是值得的。",
    "author": "用户45979",
    "likes": 417,
    "comments": 13,
    "publish_time": "2026-03-03",
    "url": "https://www.xiaohongshu.com/explore/897981807",
    "is_mock": true,
    "sentiment": 1,
    "base_sentiment": 0.9508,
    "label": "正面",
    "keywords": [
      "宝宝",
      "惠氏",
      "结块",
      "溶解度",
      "腹泻"
    ],
    "summary": [
      "但是为了宝宝的健康还是值得的",
      "消化情况良好",
      "没有出现便秘或者腹泻的情况"
    ],
    "positive_words_found": 4,
    "negative_words_found": 3
  },
  {
    "id": "mock_惠氏_1",
    "keyword": "惠氏",
    "title": "惠氏真实测评",
    "content": "买了惠氏之后有点失望。宝宝喝了之后有点上火，可能是配方不太适合。而且粉质不够细腻，冲泡的时候容易结块。",
    "author": "用户51091",
    "likes": 51,
    "comments": 33,
    "publish_time": "2026-03-03",
    "url": "https://www.xiaohongshu.com/explore/287256420",
    "is_mock": true,
    "sentiment": 0,
    "base_sentiment": 0.0026,
    "label": "负面",
    "keywords": [
      "粉质",
      "惠氏",
      "结块",
      "有点",
      "冲泡"
    ],
    "summary": [
      "买了惠氏之后有点失望",
      "宝宝喝了之后有点上火",
      "可能是配方不太适合"
    ],
    "positive_words_found": 0,
    "negative_words_found": 3
  },
  {
    "id": "mock_惠氏_2",
    "keyword": "惠氏",
    "title": "惠氏使用心得分享",
    "content": "最近给宝宝换了惠氏，感觉还不错。宝宝喝了一个月，消化情况良好，没有出现便秘或者腹泻的情况。溶解度也可以，没有结块。价格方面稍微有点贵，但是为了宝宝的健康还是值得的。",
    "author": "用户54019",
    "likes": 446,
    "comments": 9,
    "publish_time": "2026-03-03",
    "url": "https://www.xiaohongshu.com/explore/133304353",
    "is_mock": true,
    "sentiment": 1,
    "base_sentiment": 0.9508,
    "label": "正面",
    "keywords": [
      "宝宝",
      "惠氏",
      "结块",
      "溶解度",
      "腹泻"
    ],
    "summary": [
      "但是为了宝宝的健康还是值得的",
      "消化情况良好",
      "没有出现便秘或者腹泻的情况"
    ],
    "positive_words_found": 4,
    "negative_words_found": 3
  },
  {
    "id": "mock_惠氏_3",
    "keyword": "惠氏",
    "title": "惠氏真实测评",
    "content": "买了惠氏之后有点失望。宝宝喝了之后有点上火，可能是配方不太适合。而且粉质不够细腻，冲泡的时候容易结块。",
    "author": "用户38620",
    "likes": 42,
    "comments": 40,
    "publish_time": "2026-03-03",
    "url": "https://www.xiaohongshu.com/explore/189101755",
    "is_mock": true,
    "sentiment": 0,
    "base_sentiment": 0.0026,
    "label": "负面",
    "keywords": [
      "粉质",
      "惠氏",
      "结块",
      "有点",
      "冲泡"
    ],
    "summary": [
      "买了惠氏之后有点失望",
      "宝宝喝了之后有点上火",
      "可能是配方不太适合"
    ],
    "positive_words_found": 0,
    "negative_words_found": 3
  },
  {
    "id": "mock_惠氏_4",
    "keyword": "惠氏",
    "title": "惠氏使用心得分享",
    "content": "最近给宝宝换了惠氏，感觉还不错。宝宝喝了一个月，消化情况良好，没有出现便秘或者腹泻的情况。溶解度也可以，没有结块。价格方面稍微有点贵，但是为了宝宝的健康还是值得的。",
    "author": "用户74131",
    "likes": 423,
    "comments": 11,
    "publish_time": "2026-03-03",
    "url": "https://www.xiaohongshu.com/explore/529623924",
    "is_mock": true,
    "sentiment": 1,
    "base_sentiment": 0.9508,
    "label": "正面",
    "keywords": [
      "宝宝",
      "惠氏",
      "结块",
      "溶解度",
      "腹泻"
    ],
    "summary": [
      "但是为了宝宝的健康还是值得的",
      "消化情况良好",
      "没有出现便秘或者腹泻的情况"
    ],
    "positive_words_found": 4,
    "negative_words_found": 3
  },
  {
    "id": "mock_惠氏_5",
    "keyword": "惠氏",
    "title": "惠氏真实测评",
    "content": "买了惠氏之后有点失望。宝宝喝了之后有点上火，可能是配方不太适合。而且粉质不够细腻，冲泡的时候容易结块。",
    "author": "用户34081",
    "likes": 63,
    "comments": 42,
    "publish_time": "2026-03-03",
    "url": "https://www.xiaohongshu.com/explore/435379023",
    "is_mock": true,
    "sentiment": 0,
    "base_sentiment": 0.0026,
    "label": "负面",
    "keywords": [
      "粉质",
      "惠氏",
      "结块",
      "有点",
      "冲泡"
    ],
    "summary": [
      "买了惠氏之后有点失望",
      "宝宝喝了之后有点上火",
      "可能是配方不太适合"
    ],
    "positive_words_found": 0,
    "negative_words_found": 3
  },
  {
    "id": "mock_惠氏_6",
    "keyword": "惠氏",
    "title": "惠氏使用心得分享",
    "content": "最近给宝宝换了惠氏，感觉还不错。宝宝喝了一个月，消化情况良好，没有出现便秘或者腹泻的情况。溶解度也可以，没有结块。价格方面稍微有点贵，但是为了宝宝的健康还是值得的。",
    "author": "用户80651",
    "likes": 427,
    "comments": 13,
    "publish_time": "2026-03-03",
    "url": "https://www.xiaohongshu.com/explore/149270177",
    "is_mock": true,
    "sentiment": 1,
    "base_sentiment": 0.9508,
    "label": "正面",
    "keywords": [
      "宝宝",
      "惠氏",
      "结块",
      "溶解度",
      "腹泻"
    ],
    "summary": [
      "但是为了宝宝的健康还是值得的",
      "消化情况良好",
      "没有出现便秘或者腹泻的情况"
    ],
    "positive_words_found": 4,
    "negative_words_found": 3
  },
  {
    "id": "mock_惠氏_7",
    "keyword": "惠氏",
    "title": "惠氏真实测评",
    "content": "买了惠氏之后有点失望。宝宝喝了之后有点上火，可能是配方不太适合。而且粉质不够细腻，冲泡的时候容易结块。",
    "author": "用户96470",
    "likes": 37,
    "comments": 34,
    "publish_time": "2026-03-03",
    "url": "https://www.xiaohongshu.com/explore/494820647",
    "is_mock": true,
    "sentiment": 0,
    "base_sentiment": 0.0026,
    "label": "负面",
    "keywords": [
      "粉质",
      "惠氏",
      "结块",
      "有点",
      "冲泡"
    ],
    "summary": [
      "买了惠氏之后有点失望",
      "宝宝喝了之后有点上火",
      "可能是配方不太适合"
    ],
    "positive_words_found": 0,
    "negative_words_found": 3
  },
  {
    "id": "mock_惠氏_8",
    "keyword": "惠氏",
    "title": "惠氏使用心得分享",
    "content": "最近给宝宝换了惠氏，感觉还不错。宝宝喝了一个月，消化情况良好，没有出现便秘或者腹泻的情况。溶解度也可以，没有结块。价格方面稍微有点贵，但是为了宝宝的健康还是值得的。",
    "author": "用户44055",
    "likes": 436,
    "comments": 6,
    "publish_time": "2026-03-03",
    "url": "https://www.xiaohongshu.com/explore/826078938",
    "is_mock": true,
    "sentiment": 1,
    "base_sentiment": 0.9508,
    "label": "正面",
    "keywords": [
      "宝宝",
      "惠氏",
      "结块",
      "溶解度",
      "腹泻"
    ],
    "summary": [
      "但是为了宝宝的健康还是值得的",
      "消化情况良好",
      "没有出现便秘或者腹泻的情况"
    ],
    "positive_words_found": 4,
    "negative_words_found": 3
  },
  {
    "id": "mock_惠氏_9",
    "keyword": "惠氏",
    "title": "惠氏真实测评",
    "content": "买了惠氏之后有点失望。宝宝喝了之后有点上火，可能是配方不太适合。而且粉质不够细腻，冲泡的时候容易结块。",
    "author": "用户71236",
    "likes": 56,
    "comments": 41,
    "publish_time": "2026-03-03",
    "url": "https://www.xiaohongshu.com/explore/286190741",
    "is_mock": true,
    "sentiment": 0,
    "base_sentiment": 0.0026,
    "label": "负面",
    "keywords": [
      "粉质",
      "惠氏",
      "结块",
      "有点",
      "冲泡"
    ],
    "summary": [
      "买了惠氏之后有点失望",
      "宝宝喝了之后有点上火",
      "可能是配方不太适合"
    ],
    "positive_words_found": 0,
    "negative_words_found": 3
  },
  {
    "id": "mock_a2奶粉_0",
    "keyword": "a2奶粉",
    "title": "a2奶粉使用心得分享",
    "content": "最近给宝宝换了a2奶粉，感觉还不错。宝宝喝了一个月，消化情况良好，没有出现便秘或者腹泻的情况。溶解度也可以，没有结块。价格方面稍微有点贵，但是为了宝宝的健康还是值得的。",
    "author": "用户53726",
    "likes": 48,
    "comments": 48,
    "publish_time": "2026-03-03",
    "url": "https://www.xiaohongshu.com/explore/442003606",
    "is_mock": true,
    "sentiment": 1,
    "base_sentiment": 0.9789,
    "label": "正面",
    "keywords": [
      "宝宝",
      "a2",
      "结块",
      "溶解度",
      "奶粉"
    ],
    "summary": [
      "但是为了宝宝的健康还是值得的",
      "消化情况良好",
      "没有出现便秘或者腹泻的情况"
    ],
    "positive_words_found": 4,
    "negative_words_found": 3
  },
  {
    "id": "mock_a2奶粉_1",
    "keyword": "a2奶粉",
    "title": "a2奶粉真实测评",
    "content": "买了a2奶粉之后有点失望。宝宝喝了之后有点上火，可能是配方不太适合。而且粉质不够细腻，冲泡的时候容易结块。",
    "author": "用户78575",
    "likes": 117,
    "comments": 26,
    "publish_time": "2026-03-03",
    "url": "https://www.xiaohongshu.com/explore/465497489",
    "is_mock": true,
    "sentiment": 0,
    "base_sentiment": 0.0062,
    "label": "负面",
    "keywords": [
      "a2",
      "粉质",
      "结块",
      "有点",
      "冲泡"
    ],
    "summary": [
      "买了a2奶粉之后有点失望",
      "宝宝喝了之后有点上火",
      "可能是配方不太适合"
    ],
    "positive_words_found": 0,
    "negative_words_found": 3
  },
  {
    "id": "mock_a2奶粉_2",
    "keyword": "a2奶粉",
    "title": "a2奶粉使用心得分享",
    "content": "最近给宝宝换了a2奶粉，感觉还不错。宝宝喝了一个月，消化情况良好，没有出现便秘或者腹泻的情况。溶解度也可以，没有结块。价格方面稍微有点贵，但是为了宝宝的健康还是值得的。",
    "author": "用户15812",
    "likes": 42,
    "comments": 42,
    "publish_time": "2026-03-03",
    "url": "https://www.xiaohongshu.com/explore/786293188",
    "is_mock": true,
    "sentiment": 1,
    "base_sentiment": 0.9789,
    "label": "正面",
    "keywords": [
      "宝宝",
      "a2",
      "结块",
      "溶解度",
      "奶粉"
    ],
    "summary": [
      "但是为了宝宝的健康还是值得的",
      "消化情况良好",
      "没有出现便秘或者腹泻的情况"
    ],
    "positive_words_found": 4,
    "negative_words_found": 3
  },
  {
    "id": "mock_a2奶粉_3",
    "keyword": "a2奶粉",
    "title": "a2奶粉真实测评",
    "content": "买了a2奶粉之后有点失望。宝宝喝了之后有点上火，可能是配方不太适合。而且粉质不够细腻，冲泡的时候容易结块。",
    "author": "用户10664",
    "likes": 113,
    "comments": 33,
    "publish_time": "2026-03-03",
    "url": "https://www.xiaohongshu.com/explore/334213773",
    "is_mock": true,
    "sentiment": 0,
    "base_sentiment": 0.0062,
    "label": "负面",
    "keywords": [
      "a2",
      "粉质",
      "结块",
      "有点",
      "冲泡"
    ],
    "summary": [
      "买了a2奶粉之后有点失望",
      "宝宝喝了之后有点上火",
      "可能是配方不太适合"
    ],
    "positive_words_found": 0,
    "negative_words_found": 3
  },
  {
    "id": "mock_a2奶粉_4",
    "keyword": "a2奶粉",
    "title": "a2奶粉使用心得分享",
    "content": "最近给宝宝换了a2奶粉，感觉还不错。宝宝喝了一个月，消化情况良好，没有出现便秘或者腹泻的情况。溶解度也可以，没有结块。价格方面稍微有点贵，但是为了宝宝的健康还是值得的。",
    "author": "用户89129",
    "likes": 71,
    "comments": 51,
    "publish_time": "2026-03-03",
    "url": "https://www.xiaohongshu.com/explore/831652935",
    "is_mock": true,
    "sentiment": 1,
    "base_sentiment": 0.9789,
    "label": "正面",
    "keywords": [
      "宝宝",
      "a2",
      "结块",
      "溶解度",
      "奶粉"
    ],
    "summary": [
      "但是为了宝宝的健康还是值得的",
      "消化情况良好",
      "没有出现便秘或者腹泻的情况"
    ],
    "positive_words_found": 4,
    "negative_words_found": 3
  },
  {
    "id": "mock_a2奶粉_5",
    "keyword": "a2奶粉",
    "title": "a2奶粉真实测评",
    "content": "买了a2奶粉之后有点失望。宝宝喝了之后有点上火，可能是配方不太适合。而且粉质不够细腻，冲泡的时候容易结块。",
    "author": "用户65909",
    "likes": 89,
    "comments": 28,
    "publish_time": "2026-03-03",
    "url": "https://www.xiaohongshu.com/explore/356376946",
    "is_mock": true,
    "sentiment": 0,
    "base_sentiment": 0.0062,
    "label": "负面",
    "keywords": [
      "a2",
      "粉质",
      "结块",
      "有点",
      "冲泡"
    ],
    "summary": [
      "买了a2奶粉之后有点失望",
      "宝宝喝了之后有点上火",
      "可能是配方不太适合"
    ],
    "positive_words_found": 0,
    "negative_words_found": 3
  },
  {
    "id": "mock_a2奶粉_6",
    "keyword": "a2奶粉",
    "title": "a2奶粉使用心得分享",
    "content": "最近给宝宝换了a2奶粉，感觉还不错。宝宝喝了一个月，消化情况良好，没有出现便秘或者腹泻的情况。溶解度也可以，没有结块。价格方面稍微有点贵，但是为了宝宝的健康还是值得的。",
    "author": "用户54785",
    "likes": 43,
    "comments": 47,
    "publish_time": "2026-03-03",
    "url": "https://www.xiaohongshu.com/explore/239528722",
    "is_mock": true,
    "sentiment": 1,
    "base_sentiment": 0.9789,
    "label": "正面",
    "keywords": [
      "宝宝",
      "a2",
      "结块",
      "溶解度",
      "奶粉"
    ],
    "summary": [
      "但是为了宝宝的健康还是值得的",
      "消化情况良好",
      "没有出现便秘或者腹泻的情况"
    ],
    "positive_words_found": 4,
    "negative_words_found": 3
  },
  {
    "id": "mock_a2奶粉_7",
    "keyword": "a2奶粉",
    "title": "a2奶粉真实测评",
    "content": "买了a2奶粉之后有点失望。宝宝喝了之后有点上火，可能是配方不太适合。而且粉质不够细腻，冲泡的时候容易结块。",
    "author": "用户63694",
    "likes": 87,
    "comments": 28,
    "publish_time": "2026-03-03",
    "url": "https://www.xiaohongshu.com/explore/830854091",
    "is_mock": true,
    "sentiment": 0,
    "base_sentiment": 0.0062,
    "label": "负面",
    "keywords": [
      "a2",
      "粉质",
      "结块",
      "有点",
      "冲泡"
    ],
    "summary": [
      "买了a2奶粉之后有点失望",
      "宝宝喝了之后有点上火",
      "可能是配方不太适合"
    ],
    "positive_words_found": 0,
    "negative_words_found": 3
  },
  {
    "id": "mock_a2奶粉_8",
    "keyword": "a2奶粉",
    "title": "a2奶粉使用心得分享",
    "content": "最近给宝宝换了a2奶粉，感觉还不错。宝宝喝了一个月，消化情况良好，没有出现便秘或者腹泻的情况。溶解度也可以，没有结块。价格方面稍微有点贵，但是为了宝宝的健康还是值得的。",
    "author": "用户98368",
    "likes": 41,
    "comments": 51,
    "publish_time": "2026-03-03",
    "url": "https://www.xiaohongshu.com/explore/799342893",
    "is_mock": true,
    "sentiment": 1,
    "base_sentiment": 0.9789,
    "label": "正面",
    "keywords": [
      "宝宝",
      "a2",
      "结块",
      "溶解度",
      "奶粉"
    ],
    "summary": [
      "但是为了宝宝的健康还是值得的",
      "消化情况良好",
      "没有出现便秘或者腹泻的情况"
    ],
    "positive_words_found": 4,
    "negative_words_found": 3
  },
  {
    "id": "mock_a2奶粉_9",
    "keyword": "a2奶粉",
    "title": "a2奶粉真实测评",
    "content": "买了a2奶粉之后有点失望。宝宝喝了之后有点上火，可能是配方不太适合。而且粉质不够细腻，冲泡的时候容易结块。",
    "author": "用户46757",
    "likes": 93,
    "comments": 35,
    "publish_time": "2026-03-03",
    "url": "https://www.xiaohongshu.com/explore/420511714",
    "is_mock": true,
    "sentiment": 0,
    "base_sentiment": 0.0062,
    "label": "负面",
    "keywords": [
      "a2",
      "粉质",
      "结块",
      "有点",
      "冲泡"
    ],
    "summary": [
      "买了a2奶粉之后有点失望",
      "宝宝喝了之后有点上火",
      "可能是配方不太适合"
    ],
    "positive_words_found": 0,
    "negative_words_found": 3
  }
]